cub_tools/__init__.py
cub_tools/args.py
cub_tools/config.py
cub_tools/data.py
cub_tools/evaluation.py
cub_tools/layer_feature_maps.py
cub_tools/manifold.py
cub_tools/network.py
cub_tools/pytorchcv_utils.py
cub_tools/schedulers.py
cub_tools/train.py
cub_tools/transforms.py
cub_tools/triton.py
cub_tools/utils.py
cub_tools/visualize.py
cub_tools/trainer/Base.py
cub_tools/trainer/Ignite.py
cub_tools/trainer/IgniteClearML.py
cub_tools/trainer/__init__.py
cub_tools-2.5.9.dist-info/METADATA
cub_tools-2.5.9.dist-info/WHEEL
cub_tools-2.5.9.dist-info/top_level.txt
cub_tools-2.5.9.dist-info/RECORD
